isage_rag-0.1.0.1.dist-info/licenses/LICENSE
sage_libs/__init__.py
sage_libs/sage_rag/__init__.py
sage_libs/sage_rag/_register.py
sage_libs/sage_rag/_version.py
sage_libs/sage_rag/py.typed
sage_libs/sage_rag/chunkers/__init__.py
sage_libs/sage_rag/chunkers/sentence.py
sage_libs/sage_rag/chunkers/token.py
sage_libs/sage_rag/loaders/__init__.py
sage_libs/sage_rag/loaders/markdown.py
sage_libs/sage_rag/loaders/text.py
sage_libs/sage_rag/pipelines/__init__.py
sage_libs/sage_rag/pipelines/simple.py
sage_libs/sage_rag/rerankers/__init__.py
sage_libs/sage_rag/rerankers/cross_encoder.py
sage_libs/sage_rag/retrievers/__init__.py
sage_libs/sage_rag/retrievers/dense.py
isage_rag-0.1.0.1.dist-info/METADATA
isage_rag-0.1.0.1.dist-info/WHEEL
isage_rag-0.1.0.1.dist-info/top_level.txt
isage_rag-0.1.0.1.dist-info/RECORD
