Metadata-Version: 2.4
Name: isage-rag
Version: 0.1.0.1
Summary: SAGE RAG Framework - Document loaders, chunkers, retrievers for RAG pipelines
Author-email: IntelliStream Team <shuhao_zhang@hust.edu.cn>
License-Expression: MIT
Project-URL: Homepage, https://github.com/intellistream/sage-rag
Project-URL: Repository, https://github.com/intellistream/sage-rag
Keywords: RAG,retrieval,document-loader,chunker,retriever,LLM,AI
Requires-Python: >=3.10
License-File: LICENSE
Requires-Dist: pydantic>=2.0.0
Requires-Dist: typing-extensions>=4.0.0
Provides-Extra: dev
Requires-Dist: pytest>=7.0.0; extra == "dev"
Requires-Dist: pytest-asyncio>=0.21.0; extra == "dev"
Requires-Dist: ruff>=0.4.0; extra == "dev"
Dynamic: license-file
